JSONManipulator/__init__.py
JSONManipulator/exceptions.py
JSONManipulator/core/AddKey.py
JSONManipulator/core/AddObject.py
JSONManipulator/core/ChangeAllValues.py
JSONManipulator/core/ChangeValue.py
JSONManipulator/core/DeleteObject.py
JSONManipulator/core/GetInformation.py
JSONManipulator/core/__init__.py
JSONManipulator/core/set_up.py
examples/__init__.py
examples/setting_up_the_file/__init__.py
examples/setting_up_the_file/setting_up.py
examples/using_classes/__init__.py
examples/using_classes/AddKey/__init__.py
examples/using_classes/AddKey/add_key_with_default_value.py
examples/using_classes/AddObject/__init__.py
examples/using_classes/AddObject/add_object.py
examples/using_classes/ChangeAllValues/__init__.py
examples/using_classes/ChangeAllValues/change_all_values.py
examples/using_classes/ChangeValue/__init__.py
examples/using_classes/ChangeValue/change_value.py
examples/using_classes/DeleteObject/__init__.py
examples/using_classes/DeleteObject/delete_object.py
examples/using_classes/GetInformation/__init__.py
examples/using_classes/GetInformation/desc.py
examples/using_classes/GetInformation/desc_and_levenshtein.py
examples/using_classes/GetInformation/key.py
tests/__init__.py
tests/set_up/__init__.py
tests/set_up/test_set_up.py
tests/using_classes/__init__.py
tests/using_classes/AddKey/__init__.py
tests/using_classes/AddKey/test_add_key.py
tests/using_classes/AddObject/__init__.py
tests/using_classes/AddObject/test_add_object.py
tests/using_classes/ChangeAllValues/__init__.py
tests/using_classes/ChangeAllValues/test_change_all_values.py
tests/using_classes/ChangeValue/__init__.py
tests/using_classes/ChangeValue/test_change_value.py
tests/using_classes/DeleteObject/__init__.py
tests/using_classes/DeleteObject/test_delete_object.py
tests/using_classes/GetInformation/__init__.py
tests/using_classes/GetInformation/test_get_information.py
JSONManipulator-3.1.1.dist-info/AUTHORS.rst
JSONManipulator-3.1.1.dist-info/LICENSE
JSONManipulator-3.1.1.dist-info/METADATA
JSONManipulator-3.1.1.dist-info/WHEEL
JSONManipulator-3.1.1.dist-info/top_level.txt
JSONManipulator-3.1.1.dist-info/RECORD
