Metadata-Version: 2.1
Name: JSONManipulator
Version: 3.1.1
Summary: A Python package to manipulate objects in JSON files.
Home-page: https://github.com/pandrey2003/JSONManipulator
Author: Andrew Polukhin
Author-email: andrewmathematics2003@gmail.com
License: MIT
Keywords: Python JSON Objects
Platform: UNKNOWN
Classifier: Development Status :: 5 - Production/Stable
Classifier: Intended Audience :: Developers
Classifier: License :: OSI Approved :: MIT License
Classifier: Natural Language :: English
Requires-Python: ~=3.6
